tests/__init__.py
aws_supports-0.0.1.dist-info/LICENSE
aws_supports-0.0.1.dist-info/METADATA
aws_supports-0.0.1.dist-info/WHEEL
aws_supports-0.0.1.dist-info/top_level.txt
aws_supports-0.0.1.dist-info/RECORD
