Metadata-Version: 2.1
Name: aws_supports
Version: 0.0.1
Summary: UNKNOWN
Home-page: https://github.com/trinct1412/aws_support
Author: Tri Nguyen
Author-email: trinct1412@gmail.com
License: UNKNOWN
Platform: UNKNOWN
Classifier: Programming Language :: Python :: 2
Classifier: License :: OSI Approved :: MIT License
Classifier: Operating System :: OS Independent
License-File: LICENSE
